clients/__init__.py
clients/aio.py
clients/base.py
clients/py.typed
clients-1.5.dist-info/LICENSE.txt
clients-1.5.dist-info/METADATA
clients-1.5.dist-info/WHEEL
clients-1.5.dist-info/top_level.txt
clients-1.5.dist-info/RECORD
