Metadata-Version: 2.1
Name: clients
Version: 1.5
Summary: High-level HTTP clients for Python.
Author-email: Aric Coady <aric.coady@gmail.com>
License: Copyright 2022 Aric Coady
Project-URL: Homepage, https://github.com/coady/clients
Project-URL: Documentation, https://coady.github.io/clients
Project-URL: Changelog, https://github.com/coady/clients/blob/main/CHANGELOG.md
Project-URL: Issues, https://github.com/coady/clients/issues
Keywords: requests,sessions,responses,resources,asyncio
Classifier: Development Status :: 6 - Mature
Classifier: Framework :: AsyncIO
Classifier: Intended Audience :: Developers
Classifier: License :: OSI Approved :: Apache Software License
Classifier: Operating System :: OS Independent
Classifier: Programming Language :: Python :: 3
Classifier: Programming Language :: Python :: 3.8
Classifier: Programming Language :: Python :: 3.9
Classifier: Programming Language :: Python :: 3.10
Classifier: Programming Language :: Python :: 3.11
Classifier: Programming Language :: Python :: 3.12
Classifier: Topic :: Internet :: WWW/HTTP :: Session
Classifier: Topic :: Software Development :: Libraries :: Python Modules
Classifier: Typing :: Typed
Requires-Python: >=3.8
License-File: LICENSE.txt
Requires-Dist: httpx>=0.25
